{"balance": 4254.18, "day_start_balance": 3584.81, "day_date": "2026-06-28", "positions": {"ARB/USD": {"shares": 1535.4258396431294, "entry": 0.074333148, "fee_in": 0.296746, "time": "2026-06-27 02:03", "highest": 0.074333148, "psar_stop": 0.08231269}, "POL/USD": {"shares": 1515.0848769526467, "entry": 0.0716358, "fee_in": 0.282189, "time": "2026-06-27 05:17", "highest": 0.0716358, "psar_stop": 0.07601609}, "BONK/USD": {"shares": 13147383.431427771, "entry": 4.22211e-06, "fee_in": 0.144325, "time": "2026-06-27 13:09", "highest": 4.22211e-06, "psar_stop": 4.5e-06, "stop_loss": 5.0}, "AAVE/USD": {"shares": 1.947853717090031, "entry": 95.0821173, "fee_in": 0.481536, "time": "2026-06-27 20:57", "highest": 95.62, "psar_stop": 73.43397564}, "ETH/USD": {"shares": 0.11322978606731732, "entry": 1566.452835, "fee_in": 0.46116, "time": "2026-06-28 00:17", "highest": 1577.23, "stop_loss": 1.5, "take_profit": 3.0, "spike": true}}, "sl_cooldown": {}}