{"balance": 4430.69, "day_start_balance": 4032.7, "day_date": "2026-06-28", "positions": {"ARB/USD": {"shares": 1676.4302839011693, "entry": 0.074333148, "fee_in": 0.323997, "time": "2026-06-27 02:03", "highest": 0.074333148, "psar_stop": 0.08231269}, "POL/USD": {"shares": 1718.7717945923755, "entry": 0.0716358, "fee_in": 0.320127, "time": "2026-06-27 05:17", "highest": 0.0716358, "psar_stop": 0.07601609}, "BONK/USD": {"shares": 14174526.311495492, "entry": 4.22211e-06, "fee_in": 0.155601, "time": "2026-06-27 13:09", "highest": 4.22211e-06, "psar_stop": 4.5e-06, "stop_loss": 5.0}, "AAVE/USD": {"shares": 1.9457049277985818, "entry": 95.0821173, "fee_in": 0.481005, "time": "2026-06-27 20:58", "highest": 95.62, "psar_stop": 73.43397564}}, "sl_cooldown": {}}